LegendBS/__init__.py
LegendBS/abuse.py
LegendBS/banall.py
LegendBS/birthday.py
LegendBS/error.py
LegendBS/get_time.py
LegendBS/get_user.py
LegendBS/love.py
LegendBS/porn.py
LegendBS/raid.py
LegendBS/start.py
LegendBS/start_bot.py
LegendBS/start_help.py
LegendBS/startup.py
LegendBS/yup.py
pyLegendBS-0.7.dist-info/LICENSE
pyLegendBS-0.7.dist-info/METADATA
pyLegendBS-0.7.dist-info/WHEEL
pyLegendBS-0.7.dist-info/top_level.txt
pyLegendBS-0.7.dist-info/RECORD
